{
  "kind": "singleType",
  "collectionName": "heroes",
  "info": {
    "singularName": "hero",
    "pluralName": "heroes",
    "displayName": "Hero"
  },
  "options": {
    "draftAndPublish": false
  },
  "attributes": {
    "title": {
      "type": "string",
      "required": true
    },
    "animatedWords": {
      "type": "string",
      "description": "Các từ chạy thay đổi, ngăn cách bằng dấu phẩy (VD: giặt nhanh, sấy khô, diệt khuẩn)"
    },
    "subTitle": {
      "type": "string"
    },
    "backgroundImage": {
      "type": "media",
      "multiple": false,
      "required": false,
      "allowedTypes": [
        "images"
      ]
    },
    "primaryButtonText": {
      "type": "string"
    },
    "primaryButtonLink": {
      "type": "string"
    },
    "secondaryButtonText": {
      "type": "string"
    },
    "secondaryButtonLink": {
      "type": "string"
    }
  }
}
